{
    "n_res": 4,
    "n_tasks": 120,
    "rc": [ 15, 13, 14, 15 ],
    "d": [ 10, 5, 8, 4, 5, 3, 4, 4, 6, 4, 7, 4, 6, 2, 9, 5, 6, 2, 6, 1, 10, 9, 10, 1, 2, 3, 3, 8, 3, 2, 5, 4, 4, 5, 5, 9, 1, 7, 3, 5, 8, 3, 7, 8, 4, 8, 1, 2, 8, 7, 7, 3, 1, 7, 5, 7, 1, 8, 8, 10, 2, 2, 1, 9, 10, 6, 2, 3, 3, 7, 10, 4, 4, 3, 9, 7, 7, 7, 3, 10, 2, 8, 9, 5, 1, 9, 4, 2, 7, 10, 3, 8, 5, 10, 2, 5, 8, 9, 10, 3, 6, 10, 6, 7, 5, 6, 1, 4, 5, 4, 5, 6, 1, 10, 2, 9, 7, 9, 4, 2 ],
    "rr": [
        [ 0, 2, 0, 9, 0, 9, 0, 4, 0, 0, 5, 0, 0, 3, 1, 0, 0, 5, 0, 0, 0, 0, 3, 0, 10, 8, 9, 0, 6, 0, 3, 0, 0, 7, 0, 0, 0, 0, 0, 0, 0, 10, 0, 0, 0, 0, 0, 0, 0, 3, 0, 0, 0, 8, 0, 2, 6, 1, 10, 0, 0, 1, 0, 8, 0, 9, 8, 0, 9, 0, 0, 0, 0, 0, 0, 0, 5, 0, 0, 0, 0, 0, 0, 0, 0, 0, 0, 2, 0, 0, 0, 0, 0, 0, 0, 0, 0, 0, 0, 0, 0, 0, 0, 0, 0, 0, 0, 0, 0, 7, 0, 0, 0, 0, 0, 0, 0, 0, 0, 0 ],
        [ 0, 0, 0, 0, 0, 0, 0, 0, 0, 1, 0, 3, 0, 0, 0, 10, 0, 0, 0, 0, 0, 8, 0, 0, 0, 0, 0, 0, 0, 0, 0, 0, 7, 0, 0, 10, 0, 0, 0, 0, 0, 0, 0, 3, 0, 0, 0, 0, 3, 0, 0, 0, 0, 0, 0, 0, 0, 0, 0, 0, 0, 0, 0, 0, 0, 0, 0, 0, 0, 7, 0, 0, 0, 6, 0, 0, 0, 0, 0, 0, 0, 0, 1, 1, 0, 0, 0, 0, 10, 1, 0, 8, 0, 0, 8, 6, 10, 0, 0, 0, 1, 0, 0, 0, 3, 0, 0, 3, 0, 0, 8, 0, 2, 0, 9, 2, 0, 0, 0, 0 ],
        [ 7, 0, 0, 0, 0, 0, 0, 0, 1, 0, 0, 0, 0, 0, 0, 0, 1, 0, 0, 5, 0, 0, 0, 0, 0, 0, 0, 0, 0, 2, 0, 2, 0, 0, 0, 0, 0, 9, 0, 0, 0, 0, 1, 0, 0, 0, 0, 9, 0, 0, 0, 0, 0, 0, 4, 0, 0, 0, 0, 2, 5, 0, 5, 0, 0, 0, 0, 0, 0, 0, 5, 0, 6, 0, 0, 9, 0, 7, 8, 0, 0, 0, 0, 0, 0, 0, 2, 0, 0, 0, 0, 0, 0, 0, 0, 0, 0, 0, 2, 5, 0, 9, 7, 5, 0, 9, 10, 0, 3, 0, 0, 0, 0, 0, 0, 0, 4, 0, 5, 9 ],
        [ 0, 0, 10, 0, 1, 0, 2, 0, 0, 0, 0, 0, 5, 0, 0, 0, 0, 0, 6, 0, 10, 0, 0, 2, 0, 0, 0, 5, 0, 0, 0, 0, 0, 0, 7, 0, 6, 0, 1, 7, 10, 0, 0, 0, 3, 1, 7, 0, 0, 0, 2, 6, 9, 0, 0, 0, 0, 0, 0, 0, 0, 0, 0, 0, 3, 0, 0, 7, 0, 0, 0, 1, 0, 0, 2, 0, 0, 0, 0, 5, 6, 9, 0, 0, 9, 4, 0, 0, 0, 0, 9, 0, 3, 9, 0, 0, 0, 10, 0, 0, 0, 0, 0, 0, 0, 0, 0, 0, 0, 0, 0, 9, 0, 2, 0, 0, 0, 7, 0, 0 ]
    ],
    "suc": [
        [ 3, 6, 90 ],
        [ 9, 10, 26 ],
        [ 5, 11, 23 ],
        [ 4, 7, 12 ],
        [ 42, 76, 95 ],
        [ 14, 56, 81 ],
        [ 8, 11, 27 ],
        [ 21, 35, 61 ],
        [ 10, 18, 93 ],
        [ 18, 24, 41 ],
        [ 17, 44, 45 ],
        [ 13, 28, 58 ],
        [ 32, 51, 58 ],
        [ 15, 30, 65 ],
        [ 16, 20, 46 ],
        [ 25, 57, 83 ],
        [ 19, 31, 52 ],
        [ 48, 64 ],
        [ 42, 49 ],
        [ 37, 43, 78 ],
        [ 21, 22, 50 ],
        [ 33, 38, 68 ],
        [ 52, 64 ],
        [ 29, 54, 55 ],
        [ 25, 51, 60 ],
        [ 39 ],
        [ 31, 63, 96 ],
        [ 71 ],
        [ 45, 56, 70 ],
        [ 39, 41, 56 ],
        [ 34, 40, 75 ],
        [ 48, 62, 68 ],
        [ 47, 48 ],
        [ 37, 88 ],
        [ 44, 108, 115 ],
        [ 36, 59, 82 ],
        [ 70 ],
        [ 63, 71 ],
        [ 45, 51, 75 ],
        [ 50, 66, 94 ],
        [ 60, 80, 98 ],
        [ 89, 91, 110 ],
        [ 47, 67, 103 ],
        [ 49, 87, 102 ],
        [ 49, 114 ],
        [ 57, 105, 113 ],
        [ 73, 79, 106 ],
        [ 105, 112, 118 ],
        [ 61 ],
        [ 69 ],
        [ 80, 91, 99 ],
        [ 53, 77, 100 ],
        [ 76, 90, 119 ],
        [ 72, 74 ],
        [ 59, 96 ],
        [ 62, 75, 116 ],
        [ 84, 85, 104 ],
        [ 69, 94 ],
        [ 89, 95 ],
        [ 63, 66 ],
        [ 62, 77, 84 ],
        [ 69, 99, 101 ],
        [ 73, 82, 111 ],
        [ 70, 77, 103 ],
        [ 66, 67, 109 ],
        [ 79 ],
        [ 78, 97 ],
        [ 80 ],
        [ 74, 88 ],
        [ 118 ],
        [ 72, 74, 86 ],
        [ 84, 85, 92 ],
        [ 73, 83, 87 ],
        [ 89, 92 ],
        [ 83 ],
        [ 88 ],
        [ 78, 79, 86 ],
        [ 99, 116 ],
        [ 98 ],
        [ 85, 107 ],
        [ 82, 112 ],
        [ 90, 97, 102 ],
        [ 97, 117 ],
        [ 93, 104 ],
        [ 86 ],
        [ 96 ],
        [ 101 ],
        [ 92, 107 ],
        [ 95 ],
        [ 93 ],
        [ 91, 100 ],
        [ 116 ],
        [ 94, 109 ],
        [ 108 ],
        [ 108 ],
        [ 103 ],
        [ 98 ],
        [ 110 ],
        [ 100, 112 ],
        [ 102, 104 ],
        [ 101 ],
        [ 111, 115 ],
        [ 110 ],
        [ 105 ],
        [ 106, 107 ],
        [ 106 ],
        [ 109 ],
        [ 111 ],
        [ 119 ],
        [ 114 ],
        [ 114, 115 ],
        [ 113 ],
        [ 113 ],
        [ 117 ],
        [ 119 ],
        [ 118 ],
        [ 117 ],
        [],
        [],
        []
    ]
}