{
    "n_res": 4,
    "n_tasks": 90,
    "rc": [ 32, 19, 24, 23 ],
    "d": [ 3, 4, 5, 10, 2, 9, 3, 7, 8, 5, 3, 4, 6, 8, 4, 5, 3, 6, 5, 6, 2, 4, 10, 7, 1, 4, 4, 2, 4, 7, 10, 7, 6, 3, 7, 2, 9, 6, 9, 9, 4, 10, 1, 4, 5, 5, 9, 4, 3, 5, 7, 5, 10, 5, 6, 5, 5, 5, 9, 3, 1, 9, 6, 5, 1, 4, 1, 9, 3, 9, 10, 2, 3, 5, 10, 1, 8, 1, 9, 4, 2, 8, 5, 8, 4, 6, 10, 10, 8, 6 ],
    "rr": [
        [ 6, 0, 0, 9, 9, 0, 0, 0, 0, 0, 0, 0, 0, 7, 0, 0, 0, 0, 10, 9, 0, 0, 0, 0, 0, 0, 0, 3, 0, 0, 4, 0, 0, 0, 10, 0, 0, 2, 0, 0, 0, 5, 0, 1, 0, 2, 0, 0, 0, 0, 0, 0, 0, 0, 0, 0, 0, 0, 5, 0, 0, 1, 0, 4, 0, 5, 0, 8, 0, 0, 0, 5, 0, 0, 0, 0, 0, 0, 0, 0, 0, 5, 6, 0, 0, 3, 10, 3, 0, 5 ],
        [ 0, 0, 8, 0, 0, 0, 0, 0, 0, 0, 8, 0, 3, 0, 0, 0, 0, 0, 0, 0, 8, 0, 6, 0, 0, 7, 0, 0, 0, 0, 0, 6, 0, 0, 0, 10, 0, 0, 0, 4, 0, 0, 8, 0, 1, 0, 4, 0, 0, 0, 0, 0, 0, 8, 9, 0, 0, 0, 0, 0, 2, 0, 0, 0, 0, 0, 10, 0, 0, 0, 10, 0, 0, 0, 0, 0, 0, 0, 6, 0, 0, 0, 0, 5, 0, 0, 0, 0, 4, 0 ],
        [ 0, 5, 0, 0, 0, 5, 4, 0, 4, 8, 0, 8, 0, 0, 0, 0, 4, 4, 0, 0, 0, 0, 0, 0, 6, 0, 1, 0, 6, 7, 0, 0, 0, 0, 0, 0, 1, 0, 4, 0, 0, 0, 0, 0, 0, 0, 0, 0, 0, 0, 2, 0, 9, 0, 0, 0, 8, 6, 0, 0, 0, 0, 0, 0, 0, 0, 0, 0, 2, 2, 0, 0, 0, 0, 0, 0, 2, 0, 0, 9, 3, 0, 0, 0, 6, 0, 0, 0, 0, 0 ],
        [ 0, 0, 0, 0, 0, 0, 0, 1, 0, 0, 0, 0, 0, 0, 10, 6, 0, 0, 0, 0, 0, 7, 0, 2, 0, 0, 0, 0, 0, 0, 0, 0, 1, 3, 0, 0, 0, 0, 0, 0, 9, 0, 0, 0, 0, 0, 0, 8, 9, 8, 0, 1, 0, 0, 0, 3, 0, 0, 0, 4, 0, 0, 5, 0, 6, 0, 0, 0, 0, 0, 0, 0, 8, 10, 8, 5, 0, 6, 0, 0, 0, 0, 0, 0, 0, 0, 0, 0, 0, 0 ]
    ],
    "suc": [
        [ 4, 5, 6 ],
        [ 3, 9, 20 ],
        [ 10, 25, 33 ],
        [ 7, 8, 27 ],
        [ 14, 17, 18 ],
        [ 26, 42 ],
        [ 13, 16, 45 ],
        [ 73 ],
        [ 15, 28, 54 ],
        [ 11, 33 ],
        [ 19, 47 ],
        [ 12, 38, 60 ],
        [ 24, 49, 70 ],
        [ 22, 47, 53 ],
        [ 23, 59, 80 ],
        [ 82 ],
        [ 24, 30 ],
        [ 63 ],
        [ 74 ],
        [ 21 ],
        [ 42, 65 ],
        [ 29, 36 ],
        [ 43, 46, 61 ],
        [ 24, 49, 75 ],
        [ 34, 36, 55 ],
        [ 31, 41 ],
        [ 43, 52, 72 ],
        [ 50, 59 ],
        [ 30, 32 ],
        [ 35, 56, 84 ],
        [ 46 ],
        [ 40, 46 ],
        [ 39, 63 ],
        [ 36, 53, 77 ],
        [ 51, 61, 67 ],
        [ 37 ],
        [ 62 ],
        [ 89 ],
        [ 48 ],
        [ 58 ],
        [ 55, 70, 88 ],
        [ 55 ],
        [ 51, 59, 66 ],
        [ 44, 57 ],
        [ 81 ],
        [ 52, 67, 68 ],
        [ 69, 73 ],
        [ 49, 76 ],
        [ 64, 66, 71 ],
        [ 50, 79 ],
        [ 86 ],
        [ 77 ],
        [ 65, 79 ],
        [ 80 ],
        [ 75 ],
        [ 72 ],
        [ 57 ],
        [ 67, 69, 73 ],
        [ 62, 66, 70 ],
        [ 71 ],
        [ 69 ],
        [ 76 ],
        [ 64, 83 ],
        [ 71, 80, 85 ],
        [ 65 ],
        [ 87 ],
        [ 72 ],
        [ 74, 89 ],
        [ 81 ],
        [ 78 ],
        [ 78 ],
        [ 82, 86 ],
        [ 83 ],
        [ 74, 75 ],
        [ 76, 85 ],
        [ 77 ],
        [ 82, 87 ],
        [ 78 ],
        [ 79 ],
        [ 86 ],
        [ 84 ],
        [ 83, 85 ],
        [ 88 ],
        [ 84 ],
        [ 87 ],
        [ 88 ],
        [ 89 ],
        [],
        [],
        []
    ]
}